create_template_files.py
file_utils.py
spoolman2slicer.py
spoolman2slicer-0.10.0.data/data/share/spoolman2slicer/templates-orcaslicer/ABS+.json.template
spoolman2slicer-0.10.0.data/data/share/spoolman2slicer/templates-orcaslicer/ASA.json.template
spoolman2slicer-0.10.0.data/data/share/spoolman2slicer/templates-orcaslicer/TPU.json.template
spoolman2slicer-0.10.0.data/data/share/spoolman2slicer/templates-orcaslicer/default.info.template
spoolman2slicer-0.10.0.data/data/share/spoolman2slicer/templates-orcaslicer/default.json.template
spoolman2slicer-0.10.0.data/data/share/spoolman2slicer/templates-orcaslicer/filename.template
spoolman2slicer-0.10.0.data/data/share/spoolman2slicer/templates-orcaslicer/filename_for_spool.template
spoolman2slicer-0.10.0.data/data/share/spoolman2slicer/templates-prusaslicer/PLA.ini.template
spoolman2slicer-0.10.0.data/data/share/spoolman2slicer/templates-prusaslicer/default.ini.template
spoolman2slicer-0.10.0.data/data/share/spoolman2slicer/templates-prusaslicer/filename.template
spoolman2slicer-0.10.0.data/data/share/spoolman2slicer/templates-prusaslicer/filename_for_spool.template
spoolman2slicer-0.10.0.data/data/share/spoolman2slicer/templates-superslicer/ABS+.ini.template
spoolman2slicer-0.10.0.data/data/share/spoolman2slicer/templates-superslicer/ASA.ini.template
spoolman2slicer-0.10.0.data/data/share/spoolman2slicer/templates-superslicer/PLA.ini.template
spoolman2slicer-0.10.0.data/data/share/spoolman2slicer/templates-superslicer/TPU.ini.template
spoolman2slicer-0.10.0.data/data/share/spoolman2slicer/templates-superslicer/default.ini.template
spoolman2slicer-0.10.0.data/data/share/spoolman2slicer/templates-superslicer/filename.template
spoolman2slicer-0.10.0.data/data/share/spoolman2slicer/templates-superslicer/filename_for_spool.template
spoolman2slicer-0.10.0.dist-info/licenses/LICENSE
spoolman2slicer-0.10.0.dist-info/METADATA
spoolman2slicer-0.10.0.dist-info/WHEEL
spoolman2slicer-0.10.0.dist-info/entry_points.txt
spoolman2slicer-0.10.0.dist-info/top_level.txt
spoolman2slicer-0.10.0.dist-info/RECORD
