Metadata-Version: 2.4
Name: spoolman2slicer
Version: 0.10.0
Summary: Export active Spoolman spools' data to filament configuration files for 3D printer slicers
Author-email: Sebastian Andersson <sebastian@bittr.nu>
License-Expression: GPL-3.0-or-later
Project-URL: Homepage, https://github.com/bofh69/spoolman2slicer
Project-URL: Repository, https://github.com/bofh69/spoolman2slicer
Project-URL: Issues, https://github.com/bofh69/spoolman2slicer/issues
Keywords: spoolman,3d-printing,slicer,orcaslicer,prusaslicer,superslicer
Classifier: Development Status :: 4 - Beta
Classifier: Intended Audience :: End Users/Desktop
Classifier: Programming Language :: Python :: 3
Classifier: Programming Language :: Python :: 3.9
Classifier: Programming Language :: Python :: 3.10
Classifier: Programming Language :: Python :: 3.11
Classifier: Programming Language :: Python :: 3.12
Classifier: Programming Language :: Python :: 3.13
Classifier: Programming Language :: Python :: 3.14
Classifier: Topic :: Printing
Requires-Python: >=3.9
License-File: LICENSE
Requires-Dist: appdirs==1.4.4
Requires-Dist: Jinja2==3.1.6
Requires-Dist: requests==2.32.4
Requires-Dist: websockets==12.0
Dynamic: license-file
